beancount_budget/__init__.py
beancount_budget/__main__.py
beancount_budget/beancount.py
beancount_budget/cli.py
beancount_budget/config.py
beancount_budget/month.py
beancount_budget/moves.py
beancount_budget/py.typed
beancount_budget/ui.py
beancount_budget/budget/__init__.py
beancount_budget/budget/rows.py
beancount_budget/budget/util.py
beancount_budget/quota/__init__.py
beancount_budget/quota/category.py
beancount_budget/quota/quantize.py
beancount_budget/quota/types.py
beancount_budget-0.22.0.dist-info/METADATA
beancount_budget-0.22.0.dist-info/WHEEL
beancount_budget-0.22.0.dist-info/entry_points.txt
beancount_budget-0.22.0.dist-info/licenses/LICENSE
beancount_budget-0.22.0.dist-info/RECORD
