Metadata-Version: 2.4
Name: beancount-budget
Version: 0.22.0
Summary: CLI envelope budget powered by Beancount
Project-URL: Homepage, https://git.sr.ht/~goorzhel/beancount-budget
Author-email: Antonio Gurgel <antonio@goorzhel.com>
License-Expression: GPL-2.0-only
License-File: LICENSE
Classifier: License :: OSI Approved :: GNU General Public License v2 (GPLv2)
Classifier: Operating System :: OS Independent
Classifier: Programming Language :: Python :: 3
Requires-Python: >=3.12
Requires-Dist: beancount>=2.3
Requires-Dist: click~=8.0
Requires-Dist: python-dateutil~=2.7
Provides-Extra: dev
Requires-Dist: beancount-stubs>=0.1.4; extra == 'dev'
Requires-Dist: pytest-cov>=4.1; extra == 'dev'
Requires-Dist: pytest-datafiles>=3.0; extra == 'dev'
Requires-Dist: pytest>=8.0; extra == 'dev'
Requires-Dist: types-python-dateutil; extra == 'dev'
